graphpipe_tf-1.0.4.data/purelib/graphpipe_tf/__init__.py
graphpipe_tf-1.0.4.data/purelib/graphpipe_tf/layers.py
graphpipe_tf-1.0.4.data/purelib/graphpipe_tf/ops.py
graphpipe_tf-1.0.4.data/purelib/graphpipe_tf/remote_op.so
graphpipe_tf-1.0.4.dist-info/METADATA
graphpipe_tf-1.0.4.dist-info/RECORD
graphpipe_tf-1.0.4.dist-info/WHEEL
graphpipe_tf-1.0.4.dist-info/top_level.txt
